README.md
setup.py
crackcluster/__init__.py
crackcluster/base_classes.py
crackcluster/body_classes.py
crackcluster/cluster_classes.py
crackcluster/constants.py
crackcluster.egg-info/PKG-INFO
crackcluster.egg-info/SOURCES.txt
crackcluster.egg-info/dependency_links.txt
crackcluster.egg-info/requires.txt
crackcluster.egg-info/top_level.txt
scripts/cluster.py
scripts/solar_system.py